[
  {
    "rootfile": 20803,
    "callNumber": "ART File A215 no.3 PHOTO (size XS)",
    "pageNumber": "back outside cover",
    "multiPageSortOrder": 0,
    "title": "Maude Adams as Juliet, 1899 [graphic].",
    "author": "",
    "imprintOrigin": "[New York? : s.n.], 1899.",
    "bibId": 249046,
    "holdingsId": 321201,
    "lunaObjectId": 117952,
    "lunaImageId": 267576,
    "lunaURL": "http://luna.folger.edu/luna/servlet/detail/FOLGERCM1~6~6~267576~117952",
    "size4jpgURL": "http://luna.folger.edu:80/MediaManager/srvr?mediafile=/Size4/FOLGERCM1-6-NA/1118/020803.jpg",
    "size5jpgURL": "http://luna.folger.edu:80/MediaManager/srvr?mediafile=/JP2K/FOLGERCM1-6-NA/1118/020803.jp2&level=2&width=1082&height=1601",
    "size6jpgURL": "http://luna.folger.edu:80/MediaManager/srvr?mediafile=/JP2K/FOLGERCM1-6-NA/1118/020803.jp2&level=1&width=2164&height=3202",
    "size7jpgURL": "http://luna.folger.edu:80/MediaManager/srvr?mediafile=/JP2K/FOLGERCM1-6-NA/1118/020803.jp2&width=4330&height=6405",
    "dateCreated": "2014-12-30T15:31:05Z",
    "dateUpdated": "2014-12-30T15:31:06Z"
  },
  {
    "rootfile": 24370,
    "callNumber": "ART File T329 no.47 PHOTO (size XS)",
    "pageNumber": "p.421 (sig. Hhh3 recto)",
    "multiPageSortOrder": 0,
    "title": "Miss Ellen Terry as \"Juliet\" [in Shakespeare's Romeo and Juliet] [graphic] / Window & Grove.",
    "author": "Window & Grove, photographer.",
    "imprintOrigin": "[London : s.n., 1882?]",
    "bibId": 254670,
    "holdingsId": 334435,
    "lunaObjectId": 119729,
    "lunaImageId": 276466,
    "lunaURL": "http://luna.folger.edu/luna/servlet/detail/FOLGERCM1~6~6~276466~119729",
    "size4jpgURL": "http://luna.folger.edu:80/MediaManager/srvr?mediafile=/Size4/FOLGERCM1-6-NA/1118/024370.jpg",
    "size5jpgURL": "http://luna.folger.edu:80/MediaManager/srvr?mediafile=/JP2K/FOLGERCM1-6-NA/1118/024370.jp2&level=2&width=1134&height=1668",
    "size6jpgURL": "http://luna.folger.edu:80/MediaManager/srvr?mediafile=/JP2K/FOLGERCM1-6-NA/1118/024370.jp2&level=1&width=2270&height=3337",
    "size7jpgURL": "http://luna.folger.edu:80/MediaManager/srvr?mediafile=/JP2K/FOLGERCM1-6-NA/1118/024370.jp2&width=4540&height=6674",
    "dateCreated": "2014-12-30T15:44:56Z",
    "dateUpdated": "2014-12-30T15:44:56Z"
  },
 {
    "rootfile": 24371,
    "callNumber": "ART File T329 no.48 PHOTO (size XS)",
    "pageNumber": "p.421 (sig. Hhh3 recto)",
    "multiPageSortOrder": 0,
    "title": "Miss Ellen Terry as \"Juliet\" [in Shakespeare's Romeo and Juliet] [graphic] / Window & Grove.",
    "author": "Window & Grove, photographer.",
    "imprintOrigin": "[London : s.n., 1882?]",
    "bibId": 254670,
    "holdingsId": 334436,
    "lunaObjectId": 119730,
    "lunaImageId": 276471,
    "lunaURL": "http://luna.folger.edu/luna/servlet/detail/FOLGERCM1~6~6~276471~119730",
    "size4jpgURL": "http://luna.folger.edu:80/MediaManager/srvr?mediafile=/Size4/FOLGERCM1-6-NA/1118/024371.jpg",
    "size5jpgURL": "http://luna.folger.edu:80/MediaManager/srvr?mediafile=/JP2K/FOLGERCM1-6-NA/1118/024371.jp2&level=2&width=1136&height=1682",
    "size6jpgURL": "http://luna.folger.edu:80/MediaManager/srvr?mediafile=/JP2K/FOLGERCM1-6-NA/1118/024371.jp2&level=1&width=2274&height=3365",
    "size7jpgURL": "http://luna.folger.edu:80/MediaManager/srvr?mediafile=/JP2K/FOLGERCM1-6-NA/1118/024371.jp2&width=4548&height=6730",
    "dateCreated": "2014-12-30T15:44:57Z",
    "dateUpdated": "2014-12-30T15:44:57Z"
  },
  {
    "rootfile": 119642,
    "callNumber": "Bill Box G2 D84 1813-14. No. 141. Copy 2",
    "pageNumber": "C3v || C4r",
    "multiPageSortOrder": 0,
    "title": "Playbill for MOV on 5 March 1814, Drury Lane",
    "author": "",
    "imprintOrigin": "1814",
    "bibId": 0,
    "holdingsId": 0,
    "lunaObjectId": 204081,
    "lunaImageId": 1207867,
    "lunaURL": "http://luna.folger.edu/luna/servlet/detail/FOLGERCM1~6~6~1207867~204081",
    "size4jpgURL": "http://luna.folger.edu:80/MediaManager/srvr?mediafile=/Size4/FOLGERCM1~6~6/630/119642.jpg",
    "size5jpgURL": "http://luna.folger.edu:80/MediaManager/srvr?mediafile=/JP2K/FOLGERCM1~6~6/630/119642.jp2&level=2&width=1092&height=1629",
    "size6jpgURL": "http://luna.folger.edu:80/MediaManager/srvr?mediafile=/JP2K/FOLGERCM1~6~6/630/119642.jp2&level=1&width=2185&height=3259",
    "size7jpgURL": "http://luna.folger.edu:80/MediaManager/srvr?mediafile=/JP2K/FOLGERCM1~6~6/630/119642.jp2&width=4371&height=6518",
    "dateCreated": "2016-06-20T17:28:01Z",
    "dateUpdated": "2016-06-20T17:28:02Z"
  },
  {
    "rootfile": 3348,
    "callNumber": "Bill Box G2 D84 1758-59",
    "pageNumber": "no. 5",
    "multiPageSortOrder": 0,
    "title": "London. Drury Lane. 1758-1759. Playbills.",
    "author": "",
    "imprintOrigin": "1758-59",
    "bibId": 0,
    "holdingsId": 0,
    "lunaObjectId": 121603,
    "lunaImageId": 289429,
    "lunaURL": "http://luna.folger.edu/luna/servlet/detail/FOLGERCM1~6~6~289429~121603",
    "size4jpgURL": "http://luna.folger.edu:80/MediaManager/srvr?mediafile=/Size4/FOLGERCM1-6-NA/1125/003348.jpg",
    "size5jpgURL": "http://luna.folger.edu:80/MediaManager/srvr?mediafile=/JP2K/FOLGERCM1-6-NA/1125/003348.jp2&level=2&width=1101&height=1634",
    "size6jpgURL": "http://luna.folger.edu:80/MediaManager/srvr?mediafile=/JP2K/FOLGERCM1-6-NA/1125/003348.jp2&level=1&width=2203&height=3268",
    "size7jpgURL": "http://luna.folger.edu:80/MediaManager/srvr?mediafile=/JP2K/FOLGERCM1-6-NA/1125/003348.jp2&width=4407&height=6536",
    "dateCreated": "2014-12-30T16:15:01Z",
    "dateUpdated": "2014-12-30T16:15:01Z"
  },
  {
    "rootfile": 52468,
    "callNumber": "Bill BOX G2 D84 1740-1741",
    "pageNumber": "plate inserted after p.32, right side",
    "multiPageSortOrder": 0,
    "title": "Merchant of Venice, Drury Lane Playbill",
    "author": "",
    "imprintOrigin": "Feb. 13, 1741",
    "bibId": 0,
    "holdingsId": 0,
    "lunaObjectId": 145485,
    "lunaImageId": 665474,
    "lunaURL": "http://luna.folger.edu/luna/servlet/detail/FOLGERCM1~6~6~665474~145485",
    "size4jpgURL": "http://luna.folger.edu:80/MediaManager/srvr?mediafile=/Size4/FOLGERCM1-6-NA/1224/052468.jpg",
    "size5jpgURL": "http://luna.folger.edu:80/MediaManager/srvr?mediafile=/JP2K/FOLGERCM1-6-NA/1224/052468.jp2&level=2&width=2637&height=2082",
    "size6jpgURL": "http://luna.folger.edu:80/MediaManager/srvr?mediafile=/JP2K/FOLGERCM1-6-NA/1224/052468.jp2&level=1&width=5274&height=4164",
    "size7jpgURL": "",
    "dateCreated": "2014-12-30T15:33:35Z",
    "dateUpdated": "2014-12-30T15:33:35Z"
  },
  {
    "rootfile": 56122,
    "callNumber": "Bill Box G2 D84 1754-55 no.1",
    "pageNumber": "fol. [8]v: \"Carta Com[w/~] Glonc[w/~]",
    "multiPageSortOrder": 0,
    "title": "Playbill for Garrick's Romeo and Juliet",
    "author": "",
    "imprintOrigin": "1754",
    "bibId": 0,
    "holdingsId": 0,
    "lunaObjectId": 157682,
    "lunaImageId": 871285,
    "lunaURL": "http://luna.folger.edu/luna/servlet/detail/FOLGERCM1~6~6~871285~157682",
    "size4jpgURL": "http://luna.folger.edu:80/MediaManager/srvr?mediafile=/Size4/FOLGERCM1-6-NA/1386/056122.jpg",
    "size5jpgURL": "http://luna.folger.edu:80/MediaManager/srvr?mediafile=/JP2K/FOLGERCM1-6-NA/1386/056122.jp2&level=2&width=1078&height=1587",
    "size6jpgURL": "http://luna.folger.edu:80/MediaManager/srvr?mediafile=/JP2K/FOLGERCM1-6-NA/1386/056122.jp2&level=1&width=2156&height=3174",
    "size7jpgURL": "http://luna.folger.edu:80/MediaManager/srvr?mediafile=/JP2K/FOLGERCM1-6-NA/1386/056122.jp2&width=4313&height=6349",
    "dateCreated": "2014-12-30T17:17:39Z",
    "dateUpdated": "2014-12-30T17:17:39Z"
  },
  {
    "rootfile": 5831,
    "callNumber": "BILL Box G2 D84 1756-57, No. 3",
    "pageNumber": "2l3r",
    "multiPageSortOrder": 0,
    "title": "[Playbill] Lethe",
    "author": "London. Drury Lane.",
    "imprintOrigin": "December 17 [1756]",
    "bibId": 0,
    "holdingsId": 0,
    "lunaObjectId": 107702,
    "lunaImageId": 119711,
    "lunaURL": "http://luna.folger.edu/luna/servlet/detail/FOLGERCM1~6~6~119711~107702",
    "size4jpgURL": "http://luna.folger.edu:80/MediaManager/srvr?mediafile=/Size4/FOLGERCM1-6-NA/1070/005831.jpg",
    "size5jpgURL": "http://luna.folger.edu:80/MediaManager/srvr?mediafile=/JP2K/FOLGERCM1-6-NA/1070/005831.jp2&level=2&width=2163&height=2913",
    "size6jpgURL": "http://luna.folger.edu:80/MediaManager/srvr?mediafile=/JP2K/FOLGERCM1-6-NA/1070/005831.jp2&level=1&width=4327&height=5826",
    "size7jpgURL": "",
    "dateCreated": "2014-12-30T17:24:19Z",
    "dateUpdated": "2014-12-30T17:24:19Z"
  },
  {
    "rootfile": 6223,
    "callNumber": "BILL Box G2 D84 1753-54, No. 1",
    "pageNumber": "5 recto",
    "multiPageSortOrder": 0,
    "title": "[Playbill] The Lying Valet",
    "author": "London. Drury Lane.",
    "imprintOrigin": "October 4 [1753]",
    "bibId": 0,
    "holdingsId": 0,
    "lunaObjectId": 101863,
    "lunaImageId": 21637,
    "lunaURL": "http://luna.folger.edu/luna/servlet/detail/FOLGERCM1~6~6~21637~101863",
    "size4jpgURL": "http://luna.folger.edu:80/MediaManager/srvr?mediafile=/Size4/FOLGERCM1-6-NA/1022/006223.jpg",
    "size5jpgURL": "http://luna.folger.edu:80/MediaManager/srvr?mediafile=/JP2K/FOLGERCM1-6-NA/1022/006223.jp2&level=2&width=1689&height=2716",
    "size6jpgURL": "http://luna.folger.edu:80/MediaManager/srvr?mediafile=/JP2K/FOLGERCM1-6-NA/1022/006223.jp2&level=1&width=3379&height=5432",
    "size7jpgURL": "",
    "dateCreated": "2014-12-30T16:43:58Z",
    "dateUpdated": "2014-12-30T16:43:58Z"
  },
  {
    "rootfile": 6224,
    "callNumber": "BILL Box G2 D84 1760-61 No. 40",
    "pageNumber": "10 recto",
    "multiPageSortOrder": 0,
    "title": "Playbill. Every Man in his Humour",
    "author": "London. Drury Lane.",
    "imprintOrigin": "December 31 [1760]",
    "bibId": 0,
    "holdingsId": 0,
    "lunaObjectId": 101864,
    "lunaImageId": 21680,
    "lunaURL": "http://luna.folger.edu/luna/servlet/detail/FOLGERCM1~6~6~21680~101864",
    "size4jpgURL": "http://luna.folger.edu:80/MediaManager/srvr?mediafile=/Size4/FOLGERCM1-6-NA/1022/006224.jpg",
    "size5jpgURL": "http://luna.folger.edu:80/MediaManager/srvr?mediafile=/JP2K/FOLGERCM1-6-NA/1022/006224.jp2&level=2&width=2269&height=2938",
    "size6jpgURL": "http://luna.folger.edu:80/MediaManager/srvr?mediafile=/JP2K/FOLGERCM1-6-NA/1022/006224.jp2&level=1&width=4539&height=5877",
    "size7jpgURL": "",
    "dateCreated": "2014-12-30T16:43:59Z",
    "dateUpdated": "2014-12-30T16:43:59Z"
  },
  {
    "rootfile": 6295,
    "callNumber": "BILL Box G2 D84 1766-67 no.4",
    "pageNumber": "page 95",
    "multiPageSortOrder": 0,
    "title": "Playbill: Clandestine Marriage [and] Much ado about nothing",
    "author": "",
    "imprintOrigin": "October 22, 1766",
    "bibId": 0,
    "holdingsId": 0,
    "lunaObjectId": 100069,
    "lunaImageId": 1339,
    "lunaURL": "http://luna.folger.edu/luna/servlet/detail/FOLGERCM1~6~6~1339~100069",
    "size4jpgURL": "http://luna.folger.edu:80/MediaManager/srvr?mediafile=/Size4/Folger-1-NA/1001/006295.jpg",
    "size5jpgURL": "http://luna.folger.edu:80/MediaManager/srvr?mediafile=/JP2K/Folger-1-NA/1001/006295.jp2&level=2&width=2039&height=2944",
    "size6jpgURL": "http://luna.folger.edu:80/MediaManager/srvr?mediafile=/JP2K/Folger-1-NA/1001/006295.jp2&level=1&width=4079&height=5889",
    "size7jpgURL": "",
    "dateCreated": "2014-12-30T16:24:31Z",
    "dateUpdated": "2014-12-30T16:24:31Z"
  },
  {
    "rootfile": 6354,
    "callNumber": "BILL Box G2 D84 1775-76 no. 6 copy 2",
    "pageNumber": "p. 237",
    "multiPageSortOrder": 0,
    "title": "[Playbill] The Wonder!",
    "author": "London. Drury Lane.",
    "imprintOrigin": "June 10 [1776]",
    "bibId": 0,
    "holdingsId": 0,
    "lunaObjectId": 100076,
    "lunaImageId": 1420,
    "lunaURL": "http://luna.folger.edu/luna/servlet/detail/FOLGERCM1~6~6~1420~100076",
    "size4jpgURL": "http://luna.folger.edu:80/MediaManager/srvr?mediafile=/Size4/Folger-1-NA/1001/006354.jpg",
    "size5jpgURL": "http://luna.folger.edu:80/MediaManager/srvr?mediafile=/JP2K/Folger-1-NA/1001/006354.jp2&level=2&width=1941&height=2921",
    "size6jpgURL": "http://luna.folger.edu:80/MediaManager/srvr?mediafile=/JP2K/Folger-1-NA/1001/006354.jp2&level=1&width=3882&height=5842",
    "size7jpgURL": "",
    "dateCreated": "2014-12-30T16:24:35Z",
    "dateUpdated": "2014-12-30T16:24:35Z"
  },
  {
    "rootfile": 6496,
    "callNumber": "BILL Box G2 D84 1752-53 no.1",
    "pageNumber": "[21]",
    "multiPageSortOrder": 0,
    "title": "Drury Lane playbill: Every Man in his Humour and The Double Disappointment",
    "author": "",
    "imprintOrigin": "31 March [1753]",
    "bibId": 0,
    "holdingsId": 0,
    "lunaObjectId": 107784,
    "lunaImageId": 121127,
    "lunaURL": "http://luna.folger.edu/luna/servlet/detail/FOLGERCM1~6~6~121127~107784",
    "size4jpgURL": "http://luna.folger.edu:80/MediaManager/srvr?mediafile=/Size4/FOLGERCM1-6-NA/1070/006496.jpg",
    "size5jpgURL": "http://luna.folger.edu:80/MediaManager/srvr?mediafile=/JP2K/FOLGERCM1-6-NA/1070/006496.jp2&level=2&width=2248&height=2988",
    "size6jpgURL": "http://luna.folger.edu:80/MediaManager/srvr?mediafile=/JP2K/FOLGERCM1-6-NA/1070/006496.jp2&level=1&width=4497&height=5976",
    "size7jpgURL": "",
    "dateCreated": "2014-12-30T17:24:41Z",
    "dateUpdated": "2014-12-30T17:24:41Z"
  },
  {
    "rootfile": 6497,
    "callNumber": "BILL Box G2 D84 1757-58 no.1",
    "pageNumber": "[60]",
    "multiPageSortOrder": 0,
    "title": "Drury Lane Playbill: Tempest and Harlequin Ranger",
    "author": "",
    "imprintOrigin": "11 November [1757]",
    "bibId": 0,
    "holdingsId": 0,
    "lunaObjectId": 107785,
    "lunaImageId": 121133,
    "lunaURL": "http://luna.folger.edu/luna/servlet/detail/FOLGERCM1~6~6~121133~107785",
    "size4jpgURL": "http://luna.folger.edu:80/MediaManager/srvr?mediafile=/Size4/FOLGERCM1-6-NA/1070/006497.jpg",
    "size5jpgURL": "http://luna.folger.edu:80/MediaManager/srvr?mediafile=/JP2K/FOLGERCM1-6-NA/1070/006497.jp2&level=2&width=1099&height=1551",
    "size6jpgURL": "http://luna.folger.edu:80/MediaManager/srvr?mediafile=/JP2K/FOLGERCM1-6-NA/1070/006497.jp2&level=1&width=2200&height=3103",
    "size7jpgURL": "http://luna.folger.edu:80/MediaManager/srvr?mediafile=/JP2K/FOLGERCM1-6-NA/1070/006497.jp2&width=4400&height=6206",
    "dateCreated": "2014-12-30T17:24:41Z",
    "dateUpdated": "2014-12-30T17:24:41Z"
  },
  {
    "rootfile": 6498,
    "callNumber": "BILL Box G2 D84 1765-66 no.2",
    "pageNumber": "plate 3",
    "multiPageSortOrder": 0,
    "title": "Playbill: Romeo and Juliet and the Musical Lady",
    "author": "",
    "imprintOrigin": "17 September [1765]",
    "bibId": 0,
    "holdingsId": 0,
    "lunaObjectId": 107786,
    "lunaImageId": 121139,
    "lunaURL": "http://luna.folger.edu/luna/servlet/detail/FOLGERCM1~6~6~121139~107786",
    "size4jpgURL": "http://luna.folger.edu:80/MediaManager/srvr?mediafile=/Size4/FOLGERCM1-6-NA/1070/006498.jpg",
    "size5jpgURL": "http://luna.folger.edu:80/MediaManager/srvr?mediafile=/JP2K/FOLGERCM1-6-NA/1070/006498.jp2&level=2&width=2199&height=2975",
    "size6jpgURL": "http://luna.folger.edu:80/MediaManager/srvr?mediafile=/JP2K/FOLGERCM1-6-NA/1070/006498.jp2&level=1&width=4399&height=5950",
    "size7jpgURL": "",
    "dateCreated": "2014-12-30T17:24:41Z",
    "dateUpdated": "2014-12-30T17:24:42Z"
  }
]
